safepickle/__init__.py
safepickle/encoding.py
safepickle/safepickle.py
safepickle/types/__init__.py
safepickle/types/bytearray.py
safepickle/types/bytes.py
safepickle/types/datetime_.py
safepickle/types/defaultdict.py
safepickle/types/dict.py
safepickle/types/instance.py
safepickle/types/interface.py
safepickle/types/list.py
safepickle/types/manager.py
safepickle/types/set.py
safepickle/types/timedelta.py
safepickle/types/tuple.py
safepickle-0.2.0.dist-info/DESCRIPTION.rst
safepickle-0.2.0.dist-info/METADATA
safepickle-0.2.0.dist-info/RECORD
safepickle-0.2.0.dist-info/WHEEL
safepickle-0.2.0.dist-info/metadata.json
safepickle-0.2.0.dist-info/top_level.txt
